[
  {
    "type": "instagram",
    "product": "Advanced Posture Brace",
    "content": {
      "caption": "\u2728 The Advanced Posture Brace you've been seeing everywhere \u2728\n\nFinally got mine and WOW. Link in bio!",
      "hashtags": "#health&wellness #aesthetic #musthaves #shopnow #trending",
      "best_time": "13:00 PM or 7:00 PM"
    },
    "generated_at": "2026-02-02T08:29:55.977981",
    "scheduled_for": "2026-02-03T00:29:55.977984"
  },
  {
    "type": "tiktok",
    "product": "Portable Steamer Device",
    "content": {
      "hook": "Wait why is nobody talking about this Portable Steamer Device",
      "caption": "The Portable Steamer Device that broke my TikTok algorithm\n\nLink in bio to get yours!\n\n#fyp #viral #tiktokfinds #amazonfinds #musthaves #trending",
      "suggested_sound": "trending sound - aesthetic vibes",
      "best_time": "6:00 PM"
    },
    "generated_at": "2026-02-02T08:29:55.977999",
    "scheduled_for": "2026-02-03T02:29:55.978000"
  },
  {
    "type": "instagram",
    "product": "LED Strip Lights RGB",
    "content": {
      "caption": "\u2728 The LED Strip Lights RGB you've been seeing everywhere \u2728\n\nFinally got mine and WOW. Link in bio!",
      "hashtags": "#smarthome #aesthetic #musthaves #shopnow #trending",
      "best_time": "12:00 PM or 9:00 PM"
    },
    "generated_at": "2026-02-02T08:29:55.978010",
    "scheduled_for": "2026-02-02T09:29:55.978011"
  }
]